prunetree/__init__.py
prunetree/tree.py
prunetree-0.1.1.dist-info/LICENSE
prunetree-0.1.1.dist-info/METADATA
prunetree-0.1.1.dist-info/WHEEL
prunetree-0.1.1.dist-info/top_level.txt
prunetree-0.1.1.dist-info/RECORD
