Metadata-Version: 2.1
Name: prunetree
Version: 0.1.1
Summary: A DecisionTreeClassifier with automatic validation-based pruning
Author: Arun Sundar
Author-email: karthicksundar2001@gmail.com
License: MIT
Classifier: Programming Language :: Python :: 3
Classifier: License :: OSI Approved :: MIT License
Classifier: Operating System :: OS Independent
Requires-Python: >=3.7
License-File: LICENSE
Requires-Dist: scikit-learn>=1.0
Requires-Dist: numpy>=1.20
